{"name": "Phrases", "children": [{"name": 2012, "children": [["bbq", 34], ["charlotte", 16], ["midwood smokehouse", 15], ["midwood", 13], ["hush puppies", 7], ["pecan cobbler", 6], ["nc", 4], ["texas", 4], ["fatty brisket", 3], ["yelp", 3]]}, {"name": 2016, "children": [["bbq", 31], ["charlotte", 11], ["midwood", 7], ["hush puppies", 5], ["was", 4], ["combo platter", 4], ["carolina bbq", 4], ["carolina", 3], ["right amount", 3], ["definitely", 2]]}, {"name": 2017, "children": [["bbq", 24], ["charlotte", 10], ["midwood", 10], ["burnt ends", 7], ["beef brisket", 6], ["hush puppies", 5], ["midwood smokehouse", 4], ["oh", 4], ["carolina", 4], ["parking", 4]]}, {"name": 2018, "children": [["bbq", 28], ["midwood", 25], ["burnt ends", 13], ["charlotte", 12], ["yelp", 8], ["texas", 7], ["carolina", 6], ["mac", 6], ["hush puppies", 6], ["beef brisket", 4]]}, {"name": 2011, "children": [["bbq", 55], ["midwood smokehouse", 27], ["charlotte", 18], ["mac", 15], ["midwood", 9], ["carolina", 8], ["hush puppies", 7], ["ca n't", 5], ["mustard sauce", 5], ["brisket", 5]]}, {"name": 2014, "children": [["bbq", 29], ["midwood smokehouse", 19], ["charlotte", 9], ["carolina", 7], ["midwood", 7], ["hush puppies", 7], ["mac", 6], ["nc", 6], ["burnt ends", 6], ["yum", 4]]}, {"name": 2015, "children": [["bbq", 44], ["midwood", 16], ["charlotte", 8], ["midwood smokehouse", 5], ["mac", 4], ["carolina", 3], ["pimento cheese fries", 3], ["sauceman", 3], ["oh", 3], ["ribs", 3]]}, {"name": 2013, "children": [["bbq", 36], ["midwood", 16], ["charlotte", 14], ["burnt ends", 11], ["midwood smokehouse", 6], ["cuban", 5], ["ca n't", 5], ["mac", 4], ["hush puppies", 3], ["sides", 3]]}]}