{"name": "Phrases", "children": [{"name": 2012, "children": [["tacos el gordo", 20], ["carne asada", 19], ["vegas", 18], ["carne asada fries", 9], ["tacos", 7], ["tijuana", 6], ["carne asada tacos", 5], ["spicy pork", 5], ["el gordo", 4], ["xs", 4]]}, {"name": 2018, "children": [["tacos el gordo", 22], ["carne asada", 16], ["al pastor", 14], ["vegas", 14], ["different lines", 12], ["las vegas", 7], ["asada tacos", 7], ["yelp", 6], ["corn tortillas", 5], ["asada", 5]]}, {"name": 2017, "children": [["vegas", 19], ["tacos el gordo", 17], ["carne asada", 9], ["adobada", 8], ["multiple lines", 7], ["encore", 7], ["al pastor", 7], ["san diego", 6], ["carne asada fries", 6], ["different lines", 6]]}, {"name": 2014, "children": [["vegas", 23], ["tacos el gordo", 16], ["carne asada", 16], ["taco", 15], ["spicy pork", 10], ["adobada", 10], ["different lines", 9], ["carne asada fries", 8], ["pastor tacos", 8], ["separate lines", 7]]}, {"name": 2016, "children": [["vegas", 25], ["tacos el gordo", 22], ["carne asada fries", 7], ["ca n't", 7], ["lengua", 7], ["carne asada", 7], ["yelp", 6], ["adobada", 6], ["mexican food", 6], ["different lines", 6]]}, {"name": 2011, "children": [["tacos el gordo", 6], ["lv", 3], ["beef tongue", 2], ["earl", 2], ["sandwich", 2], ["taco place", 1], ["los parados", 1], ["w. sahara", 1], ["yelp", 1], ["'s adobada", 1]]}, {"name": 2013, "children": [["tacos el gordo", 18], ["vegas", 17], ["taco", 14], ["carne asada", 14], ["carne asada fries", 12], ["spicy pork", 10], ["adobada", 9], ["tacos", 8], ["lengua", 7], ["ca n't", 6]]}, {"name": 2015, "children": [["vegas", 4], ["tacos el gordo", 2], ["different lines", 2], ["if", 2], ["tacos", 2], ["ca n't", 2], ["asada", 2], ["multiple lines", 1], ["different kinds", 1], ["zero sense", 1]]}]}