{"name": "Phrases", "children": [{"name": 2012, "children": [["wcg", 14], ["white chocolate", 4], ["madeira", 4], ["scottsdale", 4], ["chocolate grill", 3], ["happy hour", 3], ["prime rib", 3], ["ca n't", 3], ["venyse", 3], ["vanilla ice cream", 3]]}, {"name": 2011, "children": [["wcg", 13], ["houston", 10], ["chocolate grill", 9], ["happy hour", 6], ["ca n't", 6], ["wo n't", 5], ["nice", 5], ["white chocolate", 5], ["veggie burger", 5], ["blue cheese", 4]]}, {"name": 2018, "children": [["scottsdale", 5], ["ca n't", 4], ["chocolate grill", 4], ["white chocolate brownie", 4], ["wcg", 4], ["taylor", 3], ["amanda", 3], ["wow", 3], ["overall", 2], ["timely manner", 2]]}, {"name": 2008, "children": [["wcg", 3], ["chocolate brownie", 3], ["yum", 3], ["alicia", 2], ["artichoke appetizer", 2], ["apple pie", 2], ["but", 2], ["bbq", 2], ["ca n't", 2], ["banana cream pie", 2]]}, {"name": 2007, "children": [["houston", 12], ["wcg", 4], ["chocolate grill", 4], ["ca n't", 3], ["white chocolate", 3], ["ahi tuna salad", 2], ["oh", 2], ["real thing", 2], ["club sandwich", 2], ["'s rip-off", 1]]}, {"name": 2010, "children": [["wcg", 11], ["white chocolate", 7], ["well", 5], ["crab cakes", 5], ["egg rolls", 5], ["chocolate grill", 5], ["scottsdale", 4], ["az", 3], ["overall", 3], ["phoenix", 2]]}, {"name": 2017, "children": [["maryland", 6], ["chocolate grill", 4], ["crab cakes", 4], ["bbq", 4], ["yelp", 3], ["pappadeaux", 3], ["scottsdale", 3], ["rotisserie chicken", 2], ["brussels", 2], ["steak sandwich", 2]]}, {"name": 2009, "children": [["wcg", 10], ["houston", 5], ["az", 4], ["chocolate grill", 4], ["white chocolate brownie", 4], ["great place", 4], ["ca n't", 3], ["crab cakes", 3], ["white chocolate", 3], ["arizona", 3]]}, {"name": 2016, "children": [["patrick", 5], ["veggie burger", 4], ["overall", 3], ["hubby", 3], ["lol", 3], ["ca n't", 3], ["ryan", 3], ["everyone", 2], ["white chocolate brownie", 2], ["white chocolate", 2]]}, {"name": 2015, "children": [["chocolate grill", 11], ["hey", 5], ["yelper", 5], ["white chocolate brownie", 5], ["apple pie", 5], ["chocolate brownie", 4], ["ahi tuna", 4], ["nice place", 3], ["overall", 3], ["white chocolate bread", 3]]}, {"name": 2013, "children": [["wcg", 8], ["gf", 8], ["used to", 4], ["shrimp cocktail", 4], ["chocolate grill", 3], ["bbq", 3], ["partner", 2], ["no", 2], ["prime rib", 2], ["timely manner", 2]]}, {"name": 2014, "children": [["prime rib", 4], ["ca n't", 3], ["balsamic ribeye", 2], ["great place", 2], ["dinner menu", 2], ["chocolate brownie", 2], ["whipped cream", 2], ["gift card", 1], ["dragonberry lemonade", 1], ["dragonberry", 1]]}]}